MANIFEST.in
README.md
setup.py
admin_material/__init__.py
admin_material/admin.py
admin_material/apps.py
admin_material/forms.py
admin_material/models.py
admin_material/tests.py
admin_material/urls.py
admin_material/utils.py
admin_material/views.py
admin_material/static/.gitkeep
admin_material/static/css/forms.css
admin_material/static/css/material-dashboard.css
admin_material/static/css/material-dashboard.css.map
admin_material/static/css/material-dashboard.min.css
admin_material/static/css/nucleo-icons.css
admin_material/static/css/nucleo-svg.css
admin_material/static/css/widgets.css
admin_material/static/fonts/nucleo-icons.eot
admin_material/static/fonts/nucleo-icons.svg
admin_material/static/fonts/nucleo-icons.ttf
admin_material/static/fonts/nucleo-icons.woff
admin_material/static/fonts/nucleo-icons.woff2
admin_material/static/fonts/nucleo.eot
admin_material/static/fonts/nucleo.ttf
admin_material/static/fonts/nucleo.woff
admin_material/static/fonts/nucleo.woff2
admin_material/static/img/apple-icon.png
admin_material/static/img/bg-pricing.jpg
admin_material/static/img/bg-smart-home-1.jpg
admin_material/static/img/bg-smart-home-2.jpg
admin_material/static/img/bruce-mars.jpg
admin_material/static/img/down-arrow-dark.svg
admin_material/static/img/down-arrow-white.svg
admin_material/static/img/down-arrow.svg
admin_material/static/img/drake.jpg
admin_material/static/img/favicon.png
admin_material/static/img/home-decor-1.jpg
admin_material/static/img/home-decor-2.jpg
admin_material/static/img/home-decor-3.jpg
admin_material/static/img/ivana-square.jpg
admin_material/static/img/ivana-squares.jpg
admin_material/static/img/ivancik.jpg
admin_material/static/img/kal-visuals-square.jpg
admin_material/static/img/logo-ct-dark.png
admin_material/static/img/logo-ct.png
admin_material/static/img/marie.jpg
admin_material/static/img/meeting.jpg
admin_material/static/img/office-dark.jpg
admin_material/static/img/product-12.jpg
admin_material/static/img/team-1.jpg
django_admin_material_dashboard_rtl.egg-info/PKG-INFO
django_admin_material_dashboard_rtl.egg-info/SOURCES.txt
django_admin_material_dashboard_rtl.egg-info/dependency_links.txt
django_admin_material_dashboard_rtl.egg-info/not-zip-safe
django_admin_material_dashboard_rtl.egg-info/top_level.txt
